pysolarcell/__init__.py
pysolarcell/materials.py
pysolarcell/solarcell.py
pysolarcell/spectra.py
pysolarcell/materials/CsPbI3_PSK_k.txt
pysolarcell/materials/CsPbI3_PSK_n.txt
pysolarcell/materials/Si_k.txt
pysolarcell/materials/Si_n.txt
pysolarcell/spectra/AM1.5G.txt
pysolarcell/spectra/LED1.txt
pysolarcell/spectra/LED2.txt
pysolarcell-1.3.1.dist-info/METADATA
pysolarcell-1.3.1.dist-info/WHEEL
pysolarcell-1.3.1.dist-info/top_level.txt
pysolarcell-1.3.1.dist-info/RECORD
