Metadata-Version: 2.1
Name: pysolarcell
Version: 1.3.1
Summary: Solar cell simulation software
Home-page: https://github.com/AustL/PySolarCell
Author: AustL
Author-email: 21chydra@gmail.com
License: MIT
Classifier: Programming Language :: Python :: 3
Classifier: License :: OSI Approved :: MIT License
Classifier: Operating System :: OS Independent
Requires-Python: >=3.10
Requires-Dist: sympy
Requires-Dist: numpy
Requires-Dist: pandas
Requires-Dist: matplotlib
Requires-Dist: scipy
Requires-Dist: pysmarts
